MANIFEST.in
pavement.py
paver-minilib.zip
setup.py
DistributedPydap.egg-info/PKG-INFO
DistributedPydap.egg-info/SOURCES.txt
DistributedPydap.egg-info/dependency_links.txt
DistributedPydap.egg-info/entry_points.txt
DistributedPydap.egg-info/namespace_packages.txt
DistributedPydap.egg-info/not-zip-safe
DistributedPydap.egg-info/requires.txt
DistributedPydap.egg-info/top_level.txt
pydap/__init__.py
pydap/wsgi/__init__.py
pydap/wsgi/distributed/__init__.py
pydap/wsgi/distributed/template/data/+dot+static/js/distributed.js
pydap/wsgi/distributed/template/templates/index.html